uci_janggi/__init__.py
uci_janggi/janggi.py
uci_janggi/uci_janggi.py
uci_janggi_sprinter89-1.1.2.dist-info/LICENSE
uci_janggi_sprinter89-1.1.2.dist-info/METADATA
uci_janggi_sprinter89-1.1.2.dist-info/WHEEL
uci_janggi_sprinter89-1.1.2.dist-info/top_level.txt
uci_janggi_sprinter89-1.1.2.dist-info/RECORD
