Metadata-Version: 2.1
Name: uci-janggi-sprinter89
Version: 1.1.2
Summary: A package to interact with fairy-stockfish janggi variant
Home-page: https://github.com/sprinter89/uci_janggi
Author: Heeseob Kim
Author-email: sprinter89tv@gmail.com
License: UNKNOWN
Platform: UNKNOWN
Classifier: Programming Language :: Python :: 3
Classifier: License :: OSI Approved :: MIT License
Classifier: Operating System :: Microsoft :: Windows
Requires-Python: >=3.0
